[
  {
    "elementType": "geometry",
    "stylers": [
      {
        "color": "#5f539d"
      }
    ]
  },
  {
    "elementType": "labels.text.fill",
    "stylers": [
      {
        "color": "#fffefa"
      }
    ]
  },
  {
    "elementType": "labels.text.stroke",
    "stylers": [
      {
        "color": "#52396a"
      },
      {
        "weight": 2.5
      }
    ]
  },
  {
    "featureType": "administrative.country",
    "elementType": "labels.text.fill",
    "stylers": [
      {
        "color": "#fffefa"
      }
    ]
  },
  {
    "featureType": "administrative.country",
    "elementType": "labels.text.stroke",
    "stylers": [
      {
        "color": "#514e7e"
      }
    ]
  },
  {
    "featureType": "administrative.land_parcel",
    "elementType": "geometry",
    "stylers": [
      {
        "color": "#5f539d"
      }
    ]
  },
  {
    "featureType": "administrative.land_parcel",
    "elementType": "labels.text.fill",
    "stylers": [
      {
        "color": "#ffffff"
      }
    ]
  },
  {
    "featureType": "landscape.natural",
    "elementType": "geometry",
    "stylers": [
      {
        "color": "#6f2ca5"
      }
    ]
  },
  {
    "featureType": "landscape.natural",
    "elementType": "labels.text.fill",
    "stylers": [
      {
        "color": "#fbfaff"
      }
    ]
  },
  {
    "featureType": "landscape.natural",
    "elementType": "labels.text.stroke",
    "stylers": [
      {
        "color": "#494658"
      }
    ]
  },
  {
    "featureType": "poi",
    "elementType": "geometry",
    "stylers": [
      {
        "color": "#d3991d"
      }
    ]
  },
  {
    "featureType": "poi",
    "elementType": "labels.text.fill",
    "stylers": [
      {
        "color": "#ffffff"
      }
    ]
  },
  {
    "featureType": "poi",
    "elementType": "labels.text.stroke",
    "stylers": [
      {
        "color": "#5f539d"
      }
    ]
  },
  {
    "featureType": "poi.park",
    "elementType": "labels.text.fill",
    "stylers": [
      {
        "color": "#ffffff"
      }
    ]
  },
  {
    "featureType": "poi.park",
    "elementType": "labels.text.stroke",
    "stylers": [
      {
        "color": "#452f60"
      }
    ]
  },
  {
    "featureType": "road",
    "elementType": "labels.text.fill",
    "stylers": [
      {
        "color": "#ffffff"
      }
    ]
  },
  {
    "featureType": "road",
    "elementType": "labels.text.stroke",
    "stylers": [
      {
        "color": "#55479a"
      }
    ]
  },
  {
    "featureType": "road.highway",
    "elementType": "geometry",
    "stylers": [
      {
        "color": "#bd9cc9"
      }
    ]
  },
  {
    "featureType": "road.highway",
    "elementType": "labels.text.fill",
    "stylers": [
      {
        "color": "#ffffff"
      }
    ]
  },
  {
    "featureType": "road.highway",
    "elementType": "labels.text.stroke",
    "stylers": [
      {
        "color": "#5a5298"
      }
    ]
  },
  {
    "featureType": "transit",
    "elementType": "labels.text.fill",
    "stylers": [
      {
        "color": "#ffffff"
      }
    ]
  },
  {
    "featureType": "transit",
    "elementType": "labels.text.stroke",
    "stylers": [
      {
        "color": "#425b94"
      }
    ]
  },
  {
    "featureType": "water",
    "elementType": "geometry",
    "stylers": [
      {
        "color": "#ccbddb"
      }
    ]
  },
  {
    "featureType": "water",
    "elementType": "labels.text.fill",
    "stylers": [
      {
        "color": "#502aa2"
      }
    ]
  },
  {
    "featureType": "poi",
    "stylers": [
      {
        "visibility": "off"
      }
    ]
  }
]